zope.password-5.0-py3.11-nspkg.pth
zope/password/__init__.py
zope/password/configure.zcml
zope/password/interfaces.py
zope/password/legacy.py
zope/password/password.py
zope/password/testing.py
zope/password/vocabulary.py
zope/password/zpasswd.py
zope/password/tests/__init__.py
zope/password/tests/test_password.py
zope/password/tests/test_zpasswd.py
zope.password-5.0.dist-info/LICENSE.txt
zope.password-5.0.dist-info/METADATA
zope.password-5.0.dist-info/WHEEL
zope.password-5.0.dist-info/entry_points.txt
zope.password-5.0.dist-info/namespace_packages.txt
zope.password-5.0.dist-info/top_level.txt
zope.password-5.0.dist-info/RECORD
