Metadata-Version: 2.1
Name: zope.password
Version: 5.0
Summary: Password encoding and checking utilities
Home-page: http://github.com/zopefoundation/zope.password
Author: Zope Foundation and Contributors
Author-email: zope-dev@zope.org
License: ZPL 2.1
Keywords: zope authentication password zpasswd
Classifier: Development Status :: 5 - Production/Stable
Classifier: Environment :: Web Environment
Classifier: Intended Audience :: Developers
Classifier: License :: OSI Approved :: Zope Public License
Classifier: Programming Language :: Python
Classifier: Programming Language :: Python :: 3
Classifier: Programming Language :: Python :: 3.9
Classifier: Programming Language :: Python :: 3.10
Classifier: Programming Language :: Python :: 3.11
Classifier: Programming Language :: Python :: 3.12
Classifier: Programming Language :: Python :: 3.13
Classifier: Programming Language :: Python :: Implementation :: CPython
Classifier: Programming Language :: Python :: Implementation :: PyPy
Classifier: Natural Language :: English
Classifier: Operating System :: OS Independent
Classifier: Topic :: Internet :: WWW/HTTP
Classifier: Framework :: Zope :: 3
Requires-Python: >=3.9
License-File: LICENSE.txt
Requires-Dist: setuptools
Requires-Dist: zope.component
Requires-Dist: zope.configuration
Requires-Dist: zope.interface
Provides-Extra: vocabulary
Requires-Dist: zope.schema; extra == "vocabulary"
Provides-Extra: test
Requires-Dist: zope.schema; extra == "test"
Requires-Dist: bcrypt; extra == "test"
Requires-Dist: zope.security; extra == "test"
Requires-Dist: zope.testing; extra == "test"
Requires-Dist: zope.testrunner; extra == "test"
Provides-Extra: bcrypt
Requires-Dist: bcrypt; extra == "bcrypt"
Provides-Extra: docs
Requires-Dist: Sphinx; extra == "docs"
Requires-Dist: repoze.sphinx.autointerface; extra == "docs"
